{
  "file_id": "38c39a36-ffef-408a-8dd7-52c6a6a2c45b",
  "kind": "quotation",
  "source_pdf": "C:\\Users\\chits\\OneDrive\\Documents\\GitHub\\axioms\\backend_stuff\\app\\storage\\uploads\\38c39a36-ffef-408a-8dd7-52c6a6a2c45b.pdf",
  "normalised": {
    "vendor_name": "RelateFlow CRM",
    "currency": "EUR",
    "quote_valid_until": "2026-08-27",
    "shipping_cost": 0.0,
    "discount": 0.0,
    "payment_terms": "30 days net",
    "items": [
      {
        "product_name": "Enterprise CRM Licence (100 users)",
        "sku": "RF-ENT-100",
        "quantity": 1.0,
        "unit_price": 24000.0,
        "total_price": 24000.0,
        "delivery_days": 1.0,
        "warranty_months": 12.0,
        "certifications": [
          "ISO 27001",
          "GDPR Art. 28",
          "T\u00dcV S\u00dcD"
        ],
        "notes": "Annual; German-language UI; GDPR data residency Frankfurt"
      },
      {
        "product_name": "Sales Automation Add-on",
        "sku": "RF-SA-ADD",
        "quantity": 1.0,
        "unit_price": 6000.0,
        "total_price": 6000.0,
        "delivery_days": 1.0,
        "warranty_months": 12.0,
        "certifications": [
          "ISO 27001",
          "GDPR Art. 28",
          "T\u00dcV S\u00dcD"
        ],
        "notes": "Annual; Includes lead scoring, email sequences, pipeline automation"
      },
      {
        "product_name": "Data Migration & Onboarding",
        "sku": "RF-MIGRATE",
        "quantity": 1.0,
        "unit_price": 4500.0,
        "total_price": 4500.0,
        "delivery_days": 14.0,
        "warranty_months": null,
        "certifications": [],
        "notes": "One-time; Up to 5 M records; includes 2 training sessions"
      },
      {
        "product_name": "Custom SAP ERP Integration",
        "sku": "RF-SAP-INT",
        "quantity": 1.0,
        "unit_price": 8000.0,
        "total_price": 8000.0,
        "delivery_days": 30.0,
        "warranty_months": null,
        "certifications": [
          "SAP Certified"
        ],
        "notes": "One-time; Bi-directional sync; SAP S/4HANA compatible"
      }
    ],
    "risk_flags": [
      "SAP integration billed separately if scope changes",
      "E&OE (Errors and Omissions Excepted)"
    ]
  },
  "raw_model_output": {
    "vendor_name": "RelateFlow CRM",
    "currency": "EUR",
    "quote_valid_until": "2026-08-27",
    "shipping_cost": 0,
    "discount": 0,
    "payment_terms": "30 days net",
    "items": [
      {
        "product_name": "Enterprise CRM Licence (100 users)",
        "sku": "RF-ENT-100",
        "quantity": 1,
        "unit_price": 24000.0,
        "total_price": 24000.0,
        "delivery_days": 1,
        "warranty_months": 12,
        "certifications": [
          "ISO 27001",
          "GDPR Art. 28",
          "T\u00dcV S\u00dcD"
        ],
        "notes": "Annual; German-language UI; GDPR data residency Frankfurt"
      },
      {
        "product_name": "Sales Automation Add-on",
        "sku": "RF-SA-ADD",
        "quantity": 1,
        "unit_price": 6000.0,
        "total_price": 6000.0,
        "delivery_days": 1,
        "warranty_months": 12,
        "certifications": [
          "ISO 27001",
          "GDPR Art. 28",
          "T\u00dcV S\u00dcD"
        ],
        "notes": "Annual; Includes lead scoring, email sequences, pipeline automation"
      },
      {
        "product_name": "Data Migration & Onboarding",
        "sku": "RF-MIGRATE",
        "quantity": 1,
        "unit_price": 4500.0,
        "total_price": 4500.0,
        "delivery_days": 14,
        "warranty_months": null,
        "certifications": [],
        "notes": "One-time; Up to 5 M records; includes 2 training sessions"
      },
      {
        "product_name": "Custom SAP ERP Integration",
        "sku": "RF-SAP-INT",
        "quantity": 1,
        "unit_price": 8000.0,
        "total_price": 8000.0,
        "delivery_days": 30,
        "warranty_months": null,
        "certifications": [
          "SAP Certified"
        ],
        "notes": "One-time; Bi-directional sync; SAP S/4HANA compatible"
      }
    ],
    "risk_flags": [
      "SAP integration billed separately if scope changes",
      "E&OE (Errors and Omissions Excepted)"
    ]
  }
}